{
    "name": "Eco Lanka",
    "short_name": "EcoLanka",
    "description": "Eco Lanka is a Eco Friendly Marketing site selling various Eco Friendly products partnered with local Lankan companies",
    "start_url":"index.html",
    "icons": [
        {
            "src": "android-chrome-192x192.png",
            "sizes": "192x192",
            "type": "image/png",
            "purpose": "maskable"
        },
        {
            "src": "android-chrome-512x512.png",
            "sizes": "512x512",
            "type": "image/png"
            "puprose": "maskable"
        }
    ],
    "theme_color": "#ffffff",
    "background_color": "#ffffff",
    "display": "standalone"
}
